purpura/__init__.py
purpura/py.typed
purpura-0.0.1.dist-info/WHEEL
purpura-0.0.1.dist-info/METADATA
purpura-0.0.1.dist-info/RECORD
