Metadata-Version: 2.3
Name: purpura
Version: 0.0.1
Summary: Add your description here
Keywords: chemistry
Author: Anton Siomchen
Author-email: Anton Siomchen <41703271+asiomchen@users.noreply.github.com>
License: Apache-2.0
Classifier: Development Status :: 3 - Alpha
Classifier: Intended Audience :: Science/Research
Classifier: License :: OSI Approved :: Apache Software License
Classifier: Topic :: Scientific/Engineering
Classifier: Topic :: Utilities
Classifier: Programming Language :: Python :: 3.10
Classifier: Programming Language :: Python :: 3.11
Classifier: Programming Language :: Python :: 3.12
Classifier: Programming Language :: Python :: 3 :: Only
Requires-Dist: epam-indigo>=1.34.0
Requires-Python: >=3.10
Project-URL: homepage, https://github.com/asiomchen/purpura
Project-URL: repository, https://github.com/asiomchen/purpura
